Metadata-Version: 2.4
Name: mcp-server-xigualaoshi
Version: 0.1.0
Summary: Add your description here
Requires-Python: >=3.12
Requires-Dist: dotenv>=0.9.9
Requires-Dist: mcp>=1.9.3
Requires-Dist: openai>=1.84.0
